idfm_qualite_de_service_calculateur-1.11.2.dist-info/licenses/LICENSE
offre_realisee/__init__.py
offre_realisee/config/__init__.py
offre_realisee/config/aggregation_config.py
offre_realisee/config/calendrier_scolaire_config.py
offre_realisee/config/file_extensions.py
offre_realisee/config/input_config.py
offre_realisee/config/logger.py
offre_realisee/config/offre_realisee_config.py
offre_realisee/domain/__init__.py
offre_realisee/domain/entities/__init__.py
offre_realisee/domain/entities/add_frequency.py
offre_realisee/domain/entities/drop_duplicates_heure_theorique.py
offre_realisee/domain/entities/drop_stop_without_real_time.py
offre_realisee/domain/entities/aggregation/__init__.py
offre_realisee/domain/entities/aggregation/generate_date_aggregation_lists.py
offre_realisee/domain/entities/aggregation/generate_suffix_by_aggregation.py
offre_realisee/domain/entities/calendrier_scolaire/__init__.py
offre_realisee/domain/entities/calendrier_scolaire/filter_calendrier_scolaire.py
offre_realisee/domain/entities/ponctualite/__init__.py
offre_realisee/domain/entities/ponctualite/compliance_score.py
offre_realisee/domain/entities/ponctualite/compute_ponctualite_stat_from_dataframe.py
offre_realisee/domain/entities/ponctualite/pandas_datetime_series_to_unix_timestamp_seconds.py
offre_realisee/domain/entities/ponctualite/process_stop_ponctualite.py
offre_realisee/domain/entities/ponctualite/stat_compliance_score_ponctualite.py
offre_realisee/domain/entities/regularite/__init__.py
offre_realisee/domain/entities/regularite/compliance_score.py
offre_realisee/domain/entities/regularite/compute_regularite_stat_from_dataframe.py
offre_realisee/domain/entities/regularite/matching_heure_theorique_reelle_regularite.py
offre_realisee/domain/entities/regularite/process_stop_regularite.py
offre_realisee/domain/entities/regularite/stat_compliance_score_regularite.py
offre_realisee/domain/port/__init__.py
offre_realisee/domain/port/calendrier_scolaire_file_system_handler.py
offre_realisee/domain/port/calendrier_scolaire_source_handler.py
idfm_qualite_de_service_calculateur-1.11.2.dist-info/METADATA
idfm_qualite_de_service_calculateur-1.11.2.dist-info/WHEEL
idfm_qualite_de_service_calculateur-1.11.2.dist-info/entry_points.txt
idfm_qualite_de_service_calculateur-1.11.2.dist-info/top_level.txt
idfm_qualite_de_service_calculateur-1.11.2.dist-info/RECORD
