Metadata-Version: 2.4
Name: idfm-qualite-de-service-calculateur
Version: 1.11.2
Summary: Calculateur de qualité de service basé sur les données d'offre réalisées
Maintainer-email: Ile de France Mobilitees <github@iledefrance-mobilites.fr>
License:                     GNU GENERAL PUBLIC LICENSE
Project-URL: Homepage, https://pypi.org/project/idfm-qualite-de-service-calculateur/
Project-URL: Documentation, https://iledefrancemobilites.github.io/idfm_offre_realisee_ponctualite_regularite/index.html
Project-URL: Repository, https://github.com/IleDeFranceMobilites/idfm_offre_realisee_ponctualite_regularite
License-File: LICENSE
Requires-Dist: pandas>=2.2.3
Requires-Dist: pyarrow>=19.0.1
Requires-Dist: scipy>=1.14.1
Requires-Dist: workalendar==17.0.0
Requires-Dist: multiprocess>=0.70.17
Dynamic: license-file
